{
  "text": {
    "hi": 20,
    "hello": 17,
    "hey": 19,
    "there": 49,
    "good": 12,
    "morning": 31,
    "evening": 10,
    "bye": 4,
    "goodbye": 13,
    "see": 42,
    "you": 57,
    "later": 28,
    "talk": 47,
    "to": 52,
    "soon": 43,
    "is": 24,
    "the": 48,
    "product": 38,
    "available": 3,
    "can": 5,
    "i": 22,
    "check": 6,
    "availability": 2,
    "of": 34,
    "laptop": 27,
    "do": 9,
    "have": 14,
    "headphones": 16,
    "in": 23,
    "stock": 44,
    "how": 21,
    "long": 29,
    "will": 55,
    "delivery": 7,
    "take": 46,
    "what": 53,
    "s": 41,
    "time": 51,
    "when": 54,
    "receive": 39,
    "my": 32,
    "order": 35,
    "your": 58,
    "return": 40,
    "policy": 37,
    "a": 0,
    "an": 1,
    "item": 26,
    "m": 30,
    "having": 15,
    "payment": 36,
    "issue": 25,
    "didn": 8,
    "t": 45,
    "go": 11,
    "through": 50,
    "need": 33,
    "help": 18,
    "with": 56
  },
  "intent": {
    "greet": 5,
    "goodbye": 4,
    "ask_product_availability": 1,
    "ask_delivery_time": 0,
    "ask_return_policy": 2,
    "payment_issue": 6,
    "bot_challenge": 3
  },
  "response": null,
  "action_name": {
    "action_listen": 6,
    "action_restart": 7,
    "action_session_start": 9,
    "action_default_fallback": 4,
    "action_deactivate_loop": 1,
    "action_revert_fallback_events": 8,
    "action_default_ask_affirmation": 2,
    "action_default_ask_rephrase": 3,
    "action_two_stage_fallback": 10,
    "action_unlikely_intent": 11,
    "action_back": 0,
    "action_extract_slots": 5,
    "utter_ask_delivery_time": 12,
    "utter_goodbye": 13,
    "utter_greet": 14,
    "utter_iamabot": 15,
    "utter_payment_issue": 16,
    "utter_product_availability": 17,
    "utter_return_policy": 18
  },
  "action_text": null,
  "intent_response_key": null
}